Metadata-Version: 2.1
Name: eliqonline
Version: 1.2.1
Summary: Eliq Online API Library
Home-page: https://github.com/6d66/eliq/
Author: 6d66
Author-email: 
License: UNKNOWN
Download-URL: https://github.com/6d66/eliq/tarball/1.2.1
Keywords: Eliq,Eliq Online,Eliq Online API
Platform: UNKNOWN
Provides-Extra: console
